{"nodes": [{"id": "vyra", "label": "vyra.py", "file_type": "code", "source_file": "backend\\vyra.py", "source_location": "L1"}, {"id": "vyra_build_user_memory_block", "label": "_build_user_memory_block()", "file_type": "code", "source_file": "backend\\vyra.py", "source_location": "L160"}, {"id": "vyra_call_jarvis_chat_via_ws", "label": "_call_jarvis_chat_via_ws()", "file_type": "code", "source_file": "backend\\vyra.py", "source_location": "L297"}, {"id": "vyra_jarvis_vault_get_json", "label": "_jarvis_vault_get_json()", "file_type": "code", "source_file": "backend\\vyra.py", "source_location": "L361"}, {"id": "vyra_jarvis_vault_post_json", "label": "_jarvis_vault_post_json()", "file_type": "code", "source_file": "backend\\vyra.py", "source_location": "L373"}, {"id": "vyra_jarvis_bridge_post_json", "label": "_jarvis_bridge_post_json()", "file_type": "code", "source_file": "backend\\vyra.py", "source_location": "L384"}, {"id": "vyra_jarvis_bridge_get_json", "label": "_jarvis_bridge_get_json()", "file_type": "code", "source_file": "backend\\vyra.py", "source_location": "L395"}, {"id": "vyra_get_girlfriend_instruction", "label": "get_girlfriend_instruction()", "file_type": "code", "source_file": "backend\\vyra.py", "source_location": "L1842"}, {"id": "vyra_get_bestfriend_instruction", "label": "get_bestfriend_instruction()", "file_type": "code", "source_file": "backend\\vyra.py", "source_location": "L1983"}, {"id": "vyra_get_professional_instruction", "label": "get_professional_instruction()", "file_type": "code", "source_file": "backend\\vyra.py", "source_location": "L2106"}, {"id": "vyra_get_system_instruction", "label": "get_system_instruction()", "file_type": "code", "source_file": "backend\\vyra.py", "source_location": "L2255"}, {"id": "vyra_audioloop", "label": "AudioLoop", "file_type": "code", "source_file": "backend\\vyra.py", "source_location": "L2359"}, {"id": "vyra_audioloop_init", "label": ".__init__()", "file_type": "code", "source_file": "backend\\vyra.py", "source_location": "L2360"}, {"id": "vyra_audioloop_load_environmental_settings", "label": "._load_environmental_settings()", "file_type": "code", "source_file": "backend\\vyra.py", "source_location": "L2541"}, {"id": "vyra_audioloop_flush_chat", "label": ".flush_chat()", "file_type": "code", "source_file": "backend\\vyra.py", "source_location": "L2568"}, {"id": "vyra_audioloop_inject_live_rag_context", "label": "._inject_live_rag_context()", "file_type": "code", "source_file": "backend\\vyra.py", "source_location": "L2580"}, {"id": "vyra_audioloop_run_self_improvement", "label": "._run_self_improvement()", "file_type": "code", "source_file": "backend\\vyra.py", "source_location": "L2637"}, {"id": "vyra_audioloop_run_memory_extraction", "label": "._run_memory_extraction()", "file_type": "code", "source_file": "backend\\vyra.py", "source_location": "L2652"}, {"id": "vyra_audioloop_set_speaker_mode", "label": ".set_speaker_mode()", "file_type": "code", "source_file": "backend\\vyra.py", "source_location": "L2756"}, {"id": "vyra_audioloop_set_personality_mode", "label": ".set_personality_mode()", "file_type": "code", "source_file": "backend\\vyra.py", "source_location": "L2769"}, {"id": "vyra_audioloop_switch_mode", "label": ".switch_mode()", "file_type": "code", "source_file": "backend\\vyra.py", "source_location": "L2822"}, {"id": "vyra_audioloop_update_permissions", "label": ".update_permissions()", "file_type": "code", "source_file": "backend\\vyra.py", "source_location": "L2827"}, {"id": "vyra_audioloop_set_paused", "label": ".set_paused()", "file_type": "code", "source_file": "backend\\vyra.py", "source_location": "L2831"}, {"id": "vyra_audioloop_stop", "label": ".stop()", "file_type": "code", "source_file": "backend\\vyra.py", "source_location": "L2837"}, {"id": "vyra_audioloop_resolve_tool_confirmation", "label": ".resolve_tool_confirmation()", "file_type": "code", "source_file": "backend\\vyra.py", "source_location": "L2840"}, {"id": "vyra_audioloop_clear_audio_queue", "label": ".clear_audio_queue()", "file_type": "code", "source_file": "backend\\vyra.py", "source_location": "L2856"}, {"id": "vyra_audioloop_send_frame", "label": ".send_frame()", "file_type": "code", "source_file": "backend\\vyra.py", "source_location": "L2875"}, {"id": "vyra_audioloop_analyze_scene", "label": ".analyze_scene()", "file_type": "code", "source_file": "backend\\vyra.py", "source_location": "L2942"}, {"id": "vyra_audioloop_send_realtime", "label": ".send_realtime()", "file_type": "code", "source_file": "backend\\vyra.py", "source_location": "L2983"}, {"id": "vyra_audioloop_check_speaker_identity", "label": ".check_speaker_identity()", "file_type": "code", "source_file": "backend\\vyra.py", "source_location": "L2988"}, {"id": "vyra_audioloop_analyze_environment", "label": ".analyze_environment()", "file_type": "code", "source_file": "backend\\vyra.py", "source_location": "L3041"}, {"id": "vyra_audioloop_listen_audio", "label": ".listen_audio()", "file_type": "code", "source_file": "backend\\vyra.py", "source_location": "L3156"}, {"id": "vyra_audioloop_handle_cad_request", "label": ".handle_cad_request()", "file_type": "code", "source_file": "backend\\vyra.py", "source_location": "L3350"}, {"id": "vyra_audioloop_handle_write_file", "label": ".handle_write_file()", "file_type": "code", "source_file": "backend\\vyra.py", "source_location": "L3419"}, {"id": "vyra_audioloop_handle_read_directory", "label": ".handle_read_directory()", "file_type": "code", "source_file": "backend\\vyra.py", "source_location": "L3470"}, {"id": "vyra_audioloop_handle_read_file", "label": ".handle_read_file()", "file_type": "code", "source_file": "backend\\vyra.py", "source_location": "L3487"}, {"id": "vyra_audioloop_handle_web_agent_request", "label": ".handle_web_agent_request()", "file_type": "code", "source_file": "backend\\vyra.py", "source_location": "L3505"}, {"id": "vyra_audioloop_handle_crawlee_request", "label": ".handle_crawlee_request()", "file_type": "code", "source_file": "backend\\vyra.py", "source_location": "L3524"}, {"id": "vyra_audioloop_receive_audio", "label": ".receive_audio()", "file_type": "code", "source_file": "backend\\vyra.py", "source_location": "L3537"}, {"id": "vyra_audioloop_play_audio", "label": ".play_audio()", "file_type": "code", "source_file": "backend\\vyra.py", "source_location": "L5572"}, {"id": "vyra_audioloop_flush_input_buffer", "label": "._flush_input_buffer()", "file_type": "code", "source_file": "backend\\vyra.py", "source_location": "L5632"}, {"id": "vyra_audioloop_session_keepalive", "label": "._session_keepalive()", "file_type": "code", "source_file": "backend\\vyra.py", "source_location": "L5642"}, {"id": "vyra_audioloop_get_system_snapshot", "label": "._get_system_snapshot()", "file_type": "code", "source_file": "backend\\vyra.py", "source_location": "L5667"}, {"id": "vyra_audioloop_proactive_loop", "label": "._proactive_loop()", "file_type": "code", "source_file": "backend\\vyra.py", "source_location": "L5696"}, {"id": "vyra_audioloop_get_frames", "label": ".get_frames()", "file_type": "code", "source_file": "backend\\vyra.py", "source_location": "L5776"}, {"id": "vyra_audioloop_get_frame", "label": "._get_frame()", "file_type": "code", "source_file": "backend\\vyra.py", "source_location": "L5798"}, {"id": "vyra_audioloop_get_screen", "label": "._get_screen()", "file_type": "code", "source_file": "backend\\vyra.py", "source_location": "L5811"}, {"id": "vyra_audioloop_run", "label": ".run()", "file_type": "code", "source_file": "backend\\vyra.py", "source_location": "L5817"}, {"id": "vyra_get_input_devices", "label": "get_input_devices()", "file_type": "code", "source_file": "backend\\vyra.py", "source_location": "L6312"}, {"id": "vyra_get_output_devices", "label": "get_output_devices()", "file_type": "code", "source_file": "backend\\vyra.py", "source_location": "L6325"}, {"id": "vyra_rationale_161", "label": "Build a compact, high-priority memory block from user_memory.json.\r     Separate", "file_type": "rationale", "source_file": "backend\\vyra.py", "source_location": "L161"}, {"id": "vyra_rationale_303", "label": "Control JARVIS via its websocket `/ws` endpoint and wait for the matching\r     `", "file_type": "rationale", "source_file": "backend\\vyra.py", "source_location": "L303"}, {"id": "vyra_rationale_1843", "label": "Girlfriend personality - romantic, loving, jealous", "file_type": "rationale", "source_file": "backend\\vyra.py", "source_location": "L1843"}, {"id": "vyra_rationale_1984", "label": "Best friend personality - casual, supportive, platonic", "file_type": "rationale", "source_file": "backend\\vyra.py", "source_location": "L1984"}, {"id": "vyra_rationale_2107", "label": "Professional assistant personality - formal, efficient, polite", "file_type": "rationale", "source_file": "backend\\vyra.py", "source_location": "L2107"}, {"id": "vyra_rationale_2256", "label": "Generate dynamic system instruction based on who is speaking and personality mod", "file_type": "rationale", "source_file": "backend\\vyra.py", "source_location": "L2256"}, {"id": "vyra_rationale_2542", "label": "Load environmental awareness settings from settings.json", "file_type": "rationale", "source_file": "backend\\vyra.py", "source_location": "L2542"}, {"id": "vyra_rationale_2569", "label": "Forces the current chat buffer to be written to log.", "file_type": "rationale", "source_file": "backend\\vyra.py", "source_location": "L2569"}, {"id": "vyra_rationale_2581", "label": "Query RAG store with the user's latest message and inject relevant memories.", "file_type": "rationale", "source_file": "backend\\vyra.py", "source_location": "L2581"}, {"id": "vyra_rationale_2638", "label": "Background: analyze recent conversations for corrections/gaps and store improvem", "file_type": "rationale", "source_file": "backend\\vyra.py", "source_location": "L2638"}, {"id": "vyra_rationale_2653", "label": "Background: extract people/facts/preferences from recent chat and merge into use", "file_type": "rationale", "source_file": "backend\\vyra.py", "source_location": "L2653"}, {"id": "vyra_rationale_2757", "label": "Change speaker mode between 'main_user' (girlfriend) and 'other_person' (neutral", "file_type": "rationale", "source_file": "backend\\vyra.py", "source_location": "L2757"}, {"id": "vyra_rationale_2770", "label": "Change personality mode \u2014 NO reconnect, instant persona injection.", "file_type": "rationale", "source_file": "backend\\vyra.py", "source_location": "L2770"}, {"id": "vyra_rationale_2823", "label": "Tool handler for switch_mode", "file_type": "rationale", "source_file": "backend\\vyra.py", "source_location": "L2823"}, {"id": "vyra_rationale_2857", "label": "Clears the queue of pending audio chunks to stop playback immediately.", "file_type": "rationale", "source_file": "backend\\vyra.py", "source_location": "L2857"}, {"id": "vyra_rationale_2943", "label": "Periodically analyze the visual scene for objects and context", "file_type": "rationale", "source_file": "backend\\vyra.py", "source_location": "L2943"}, {"id": "vyra_rationale_2989", "label": "Identify the speaker and update mode/context", "file_type": "rationale", "source_file": "backend\\vyra.py", "source_location": "L2989"}, {"id": "vyra_rationale_3042", "label": "Analyze background audio for environmental awareness", "file_type": "rationale", "source_file": "backend\\vyra.py", "source_location": "L3042"}, {"id": "vyra_rationale_3538", "label": "Background task to reads from the websocket and write pcm chunks to the output q", "file_type": "rationale", "source_file": "backend\\vyra.py", "source_location": "L3538"}, {"id": "vyra_rationale_5633", "label": "Helper to flush PyAudio input buffer safely in a thread", "file_type": "rationale", "source_file": "backend\\vyra.py", "source_location": "L5633"}, {"id": "vyra_rationale_5643", "label": "Sends a silent heartbeat every 25s to prevent Gemini idle-timeout disconnects.", "file_type": "rationale", "source_file": "backend\\vyra.py", "source_location": "L5643"}, {"id": "vyra_rationale_5668", "label": "Returns a one-line system context string injected at session start.", "file_type": "rationale", "source_file": "backend\\vyra.py", "source_location": "L5668"}, {"id": "vyra_rationale_5697", "label": "Checks system triggers every 90 seconds and pushes natural notifications.", "file_type": "rationale", "source_file": "backend\\vyra.py", "source_location": "L5697"}, {"id": "vyra_rationale_3089", "label": "# IMPORTANT: Don't send notifications while vyra is speaking", "file_type": "rationale", "source_file": "backend\\vyra.py", "source_location": "L3089"}, {"id": "vyra_rationale_3555", "label": "# NOTE: 'continue' removed here to allow processing transcription/tools in same", "file_type": "rationale", "source_file": "backend\\vyra.py", "source_location": "L3555"}], "edges": [{"source": "vyra", "target": "gpu_config", "relation": "imports", "confidence": "EXTRACTED", "source_file": "backend\\vyra.py", "source_location": "L1", "weight": 1.0}, {"source": "vyra", "target": "mood_music_mapper", "relation": "imports_from", "confidence": "EXTRACTED", "source_file": "backend\\vyra.py", "source_location": "L4", "weight": 1.0}, {"source": "vyra", "target": "spotify_agent", "relation": "imports_from", "confidence": "EXTRACTED", "source_file": "backend\\vyra.py", "source_location": "L5", "weight": 1.0}, {"source": "vyra", "target": "perception", "relation": "imports_from", "confidence": "EXTRACTED", "source_file": "backend\\vyra.py", "source_location": "L6", "weight": 1.0}, {"source": "vyra", "target": "output_agent", "relation": "imports_from", "confidence": "EXTRACTED", "source_file": "backend\\vyra.py", "source_location": "L7", "weight": 1.0}, {"source": "vyra", "target": "printer_agent", "relation": "imports_from", "confidence": "EXTRACTED", "source_file": "backend\\vyra.py", "source_location": "L8", "weight": 1.0}, {"source": "vyra", "target": "kasa_agent", "relation": "imports_from", "confidence": "EXTRACTED", "source_file": "backend\\vyra.py", "source_location": "L9", "weight": 1.0}, {"source": "vyra", "target": "n8n_agent", "relation": "imports_from", "confidence": "EXTRACTED", "source_file": "backend\\vyra.py", "source_location": "L10", "weight": 1.0}, {"source": "vyra", "target": "crawlee_agent", "relation": "imports_from", "confidence": "EXTRACTED", "source_file": "backend\\vyra.py", "source_location": "L12", "weight": 1.0}, {"source": "vyra", "target": "web_agent", "relation": "imports_from", "confidence": "EXTRACTED", "source_file": "backend\\vyra.py", "source_location": "L19", "weight": 1.0}, {"source": "vyra", "target": "contact_manager", "relation": "imports_from", "confidence": "EXTRACTED", "source_file": "backend\\vyra.py", "source_location": "L20", "weight": 1.0}, {"source": "vyra", "target": "cad_agent", "relation": "imports_from", "confidence": "EXTRACTED", "source_file": "backend\\vyra.py", "source_location": "L21", "weight": 1.0}, {"source": "vyra", "target": "actions_cmd_control", "relation": "imports_from", "confidence": "EXTRACTED", "source_file": "backend\\vyra.py", "source_location": "L25", "weight": 1.0}, {"source": "vyra", "target": "actions_desktop", "relation": "imports_from", "confidence": "EXTRACTED", "source_file": "backend\\vyra.py", "source_location": "L26", "weight": 1.0}, {"source": "vyra", "target": "actions_dev_agent", "relation": "imports_from", "confidence": "EXTRACTED", "source_file": "backend\\vyra.py", "source_location": "L27", "weight": 1.0}, {"source": "vyra", "target": "actions_flight_finder", "relation": "imports_from", "confidence": "EXTRACTED", "source_file": "backend\\vyra.py", "source_location": "L28", "weight": 1.0}, {"source": "vyra", "target": "actions_open_app", "relation": "imports_from", "confidence": "EXTRACTED", "source_file": "backend\\vyra.py", "source_location": "L29", "weight": 1.0}, {"source": "vyra", "target": "actions_reminder", "relation": "imports_from", "confidence": "EXTRACTED", "source_file": "backend\\vyra.py", "source_location": "L30", "weight": 1.0}, {"source": "vyra", "target": "actions_screen_processor", "relation": "imports_from", "confidence": "EXTRACTED", "source_file": "backend\\vyra.py", "source_location": "L31", "weight": 1.0}, {"source": "vyra", "target": "actions_send_message", "relation": "imports_from", "confidence": "EXTRACTED", "source_file": "backend\\vyra.py", "source_location": "L32", "weight": 1.0}, {"source": "vyra", "target": "actions_weather_report", "relation": "imports_from", "confidence": "EXTRACTED", "source_file": "backend\\vyra.py", "source_location": "L33", "weight": 1.0}, {"source": "vyra", "target": "actions_web_search", "relation": "imports_from", "confidence": "EXTRACTED", "source_file": "backend\\vyra.py", "source_location": "L34", "weight": 1.0}, {"source": "vyra", "target": "actions_win_archives", "relation": "imports_from", "confidence": "EXTRACTED", "source_file": "backend\\vyra.py", "source_location": "L43", "weight": 1.0}, {"source": "vyra", "target": "actions_win_clipboard", "relation": "imports_from", "confidence": "EXTRACTED", "source_file": "backend\\vyra.py", "source_location": "L44", "weight": 1.0}, {"source": "vyra", "target": "actions_win_env_vars", "relation": "imports_from", "confidence": "EXTRACTED", "source_file": "backend\\vyra.py", "source_location": "L45", "weight": 1.0}, {"source": "vyra", "target": "actions_win_startup", "relation": "imports_from", "confidence": "EXTRACTED", "source_file": "backend\\vyra.py", "source_location": "L46", "weight": 1.0}, {"source": "vyra", "target": "actions_win_processes", "relation": "imports_from", "confidence": "EXTRACTED", "source_file": "backend\\vyra.py", "source_location": "L47", "weight": 1.0}, {"source": "vyra", "target": "actions_win_notifications", "relation": "imports_from", "confidence": "EXTRACTED", "source_file": "backend\\vyra.py", "source_location": "L48", "weight": 1.0}, {"source": "vyra", "target": "actions_win_services", "relation": "imports_from", "confidence": "EXTRACTED", "source_file": "backend\\vyra.py", "source_location": "L49", "weight": 1.0}, {"source": "vyra", "target": "actions_win_tasks", "relation": "imports_from", "confidence": "EXTRACTED", "source_file": "backend\\vyra.py", "source_location": "L50", "weight": 1.0}, {"source": "vyra", "target": "actions_win_network", "relation": "imports_from", "confidence": "EXTRACTED", "source_file": "backend\\vyra.py", "source_location": "L51", "weight": 1.0}, {"source": "vyra", "target": "actions_win_packages", "relation": "imports_from", "confidence": "EXTRACTED", "source_file": "backend\\vyra.py", "source_location": "L52", "weight": 1.0}, {"source": "vyra", "target": "actions_win_printers", "relation": "imports_from", "confidence": "EXTRACTED", "source_file": "backend\\vyra.py", "source_location": "L53", "weight": 1.0}, {"source": "vyra", "target": "actions_win_firewall", "relation": "imports_from", "confidence": "EXTRACTED", "source_file": "backend\\vyra.py", "source_location": "L54", "weight": 1.0}, {"source": "vyra", "target": "actions_win_defender", "relation": "imports_from", "confidence": "EXTRACTED", "source_file": "backend\\vyra.py", "source_location": "L55", "weight": 1.0}, {"source": "vyra", "target": "actions_win_updates", "relation": "imports_from", "confidence": "EXTRACTED", "source_file": "backend\\vyra.py", "source_location": "L56", "weight": 1.0}, {"source": "vyra", "target": "actions_win_registry", "relation": "imports_from", "confidence": "EXTRACTED", "source_file": "backend\\vyra.py", "source_location": "L57", "weight": 1.0}, {"source": "vyra", "target": "actions_win_display", "relation": "imports_from", "confidence": "EXTRACTED", "source_file": "backend\\vyra.py", "source_location": "L58", "weight": 1.0}, {"source": "vyra", "target": "actions_win_power", "relation": "imports_from", "confidence": "EXTRACTED", "source_file": "backend\\vyra.py", "source_location": "L59", "weight": 1.0}, {"source": "vyra", "target": "actions_win_users", "relation": "imports_from", "confidence": "EXTRACTED", "source_file": "backend\\vyra.py", "source_location": "L60", "weight": 1.0}, {"source": "vyra", "target": "actions_win_audio_devices", "relation": "imports_from", "confidence": "EXTRACTED", "source_file": "backend\\vyra.py", "source_location": "L61", "weight": 1.0}, {"source": "vyra", "target": "actions_win_bluetooth", "relation": "imports_from", "confidence": "EXTRACTED", "source_file": "backend\\vyra.py", "source_location": "L62", "weight": 1.0}, {"source": "vyra", "target": "actions_win_ocr", "relation": "imports_from", "confidence": "EXTRACTED", "source_file": "backend\\vyra.py", "source_location": "L63", "weight": 1.0}, {"source": "vyra", "target": "actions_win_disk", "relation": "imports_from", "confidence": "EXTRACTED", "source_file": "backend\\vyra.py", "source_location": "L64", "weight": 1.0}, {"source": "vyra", "target": "actions_win_system_info", "relation": "imports_from", "confidence": "EXTRACTED", "source_file": "backend\\vyra.py", "source_location": "L65", "weight": 1.0}, {"source": "vyra", "target": "actions_win_event_log", "relation": "imports_from", "confidence": "EXTRACTED", "source_file": "backend\\vyra.py", "source_location": "L66", "weight": 1.0}, {"source": "vyra", "target": "actions_win_hosts", "relation": "imports_from", "confidence": "EXTRACTED", "source_file": "backend\\vyra.py", "source_location": "L67", "weight": 1.0}, {"source": "vyra", "target": "actions_win_credential", "relation": "imports_from", "confidence": "EXTRACTED", "source_file": "backend\\vyra.py", "source_location": "L68", "weight": 1.0}, {"source": "vyra", "target": "actions_win_shortcuts", "relation": "imports_from", "confidence": "EXTRACTED", "source_file": "backend\\vyra.py", "source_location": "L69", "weight": 1.0}, {"source": "vyra", "target": "actions_win_theme", "relation": "imports_from", "confidence": "EXTRACTED", "source_file": "backend\\vyra.py", "source_location": "L70", "weight": 1.0}, {"source": "vyra", "target": "actions_win_wsl", "relation": "imports_from", "confidence": "EXTRACTED", "source_file": "backend\\vyra.py", "source_location": "L71", "weight": 1.0}, {"source": "vyra", "target": "actions_win_time", "relation": "imports_from", "confidence": "EXTRACTED", "source_file": "backend\\vyra.py", "source_location": "L72", "weight": 1.0}, {"source": "vyra", "target": "actions_win_screen_record", "relation": "imports_from", "confidence": "EXTRACTED", "source_file": "backend\\vyra.py", "source_location": "L73", "weight": 1.0}, {"source": "vyra", "target": "actions_win_file_perms", "relation": "imports_from", "confidence": "EXTRACTED", "source_file": "backend\\vyra.py", "source_location": "L74", "weight": 1.0}, {"source": "vyra", "target": "actions_win_automate", "relation": "imports_from", "confidence": "EXTRACTED", "source_file": "backend\\vyra.py", "source_location": "L75", "weight": 1.0}, {"source": "vyra", "target": "actions_win_group_policy", "relation": "imports_from", "confidence": "EXTRACTED", "source_file": "backend\\vyra.py", "source_location": "L76", "weight": 1.0}, {"source": "vyra", "target": "asyncio", "relation": "imports", "confidence": "EXTRACTED", "source_file": "backend\\vyra.py", "source_location": "L87", "weight": 1.0}, {"source": "vyra", "target": "base64", "relation": "imports", "confidence": "EXTRACTED", "source_file": "backend\\vyra.py", "source_location": "L88", "weight": 1.0}, {"source": "vyra", "target": "io", "relation": "imports", "confidence": "EXTRACTED", "source_file": "backend\\vyra.py", "source_location": "L89", "weight": 1.0}, {"source": "vyra", "target": "os", "relation": "imports", "confidence": "EXTRACTED", "source_file": "backend\\vyra.py", "source_location": "L90", "weight": 1.0}, {"source": "vyra", "target": "sys", "relation": "imports", "confidence": "EXTRACTED", "source_file": "backend\\vyra.py", "source_location": "L91", "weight": 1.0}, {"source": "vyra", "target": "traceback", "relation": "imports", "confidence": "EXTRACTED", "source_file": "backend\\vyra.py", "source_location": "L92", "weight": 1.0}, {"source": "vyra", "target": "json", "relation": "imports", "confidence": "EXTRACTED", "source_file": "backend\\vyra.py", "source_location": "L93", "weight": 1.0}, {"source": "vyra", "target": "datetime", "relation": "imports", "confidence": "EXTRACTED", "source_file": "backend\\vyra.py", "source_location": "L94", "weight": 1.0}, {"source": "vyra", "target": "dotenv", "relation": "imports_from", "confidence": "EXTRACTED", "source_file": "backend\\vyra.py", "source_location": "L95", "weight": 1.0}, {"source": "vyra", "target": "cv2", "relation": "imports", "confidence": "EXTRACTED", "source_file": "backend\\vyra.py", "source_location": "L96", "weight": 1.0}, {"source": "vyra", "target": "pyaudio", "relation": "imports", "confidence": "EXTRACTED", "source_file": "backend\\vyra.py", "source_location": "L97", "weight": 1.0}, {"source": "vyra", "target": "pil_image", "relation": "imports", "confidence": "EXTRACTED", "source_file": "backend\\vyra.py", "source_location": "L98", "weight": 1.0}, {"source": "vyra", "target": "argparse", "relation": "imports", "confidence": "EXTRACTED", "source_file": "backend\\vyra.py", "source_location": "L99", "weight": 1.0}, {"source": "vyra", "target": "math", "relation": "imports", "confidence": "EXTRACTED", "source_file": "backend\\vyra.py", "source_location": "L100", "weight": 1.0}, {"source": "vyra", "target": "struct", "relation": "imports", "confidence": "EXTRACTED", "source_file": "backend\\vyra.py", "source_location": "L101", "weight": 1.0}, {"source": "vyra", "target": "time", "relation": "imports", "confidence": "EXTRACTED", "source_file": "backend\\vyra.py", "source_location": "L102", "weight": 1.0}, {"source": "vyra", "target": "psutil", "relation": "imports", "confidence": "EXTRACTED", "source_file": "backend\\vyra.py", "source_location": "L106", "weight": 1.0}, {"source": "vyra", "target": "pygetwindow", "relation": "imports", "confidence": "EXTRACTED", "source_file": "backend\\vyra.py", "source_location": "L113", "weight": 1.0}, {"source": "vyra", "target": "google", "relation": "imports_from", "confidence": "EXTRACTED", "source_file": "backend\\vyra.py", "source_location": "L118", "weight": 1.0}, {"source": "vyra", "target": "google_genai", "relation": "imports_from", "confidence": "EXTRACTED", "source_file": "backend\\vyra.py", "source_location": "L119", "weight": 1.0}, {"source": "vyra", "target": "taskgroup", "relation": "imports", "confidence": "EXTRACTED", "source_file": "backend\\vyra.py", "source_location": "L122", "weight": 1.0}, {"source": "vyra", "target": "exceptiongroup", "relation": "imports", "confidence": "EXTRACTED", "source_file": "backend\\vyra.py", "source_location": "L123", "weight": 1.0}, {"source": "vyra", "target": "tools", "relation": "imports_from", "confidence": "EXTRACTED", "source_file": "backend\\vyra.py", "source_location": "L127", "weight": 1.0}, {"source": "vyra", "target": "vyra_quantum", "relation": "imports_from", "confidence": "EXTRACTED", "source_file": "backend\\vyra.py", "source_location": "L128", "weight": 1.0}, {"source": "vyra", "target": "jarvis_bridge", "relation": "imports_from", "confidence": "EXTRACTED", "source_file": "backend\\vyra.py", "source_location": "L129", "weight": 1.0}, {"source": "vyra", "target": "vyra_build_user_memory_block", "relation": "contains", "confidence": "EXTRACTED", "source_file": "backend\\vyra.py", "source_location": "L160", "weight": 1.0}, {"source": "vyra", "target": "vyra_call_jarvis_chat_via_ws", "relation": "contains", "confidence": "EXTRACTED", "source_file": "backend\\vyra.py", "source_location": "L297", "weight": 1.0}, {"source": "vyra", "target": "vyra_jarvis_vault_get_json", "relation": "contains", "confidence": "EXTRACTED", "source_file": "backend\\vyra.py", "source_location": "L361", "weight": 1.0}, {"source": "vyra", "target": "vyra_jarvis_vault_post_json", "relation": "contains", "confidence": "EXTRACTED", "source_file": "backend\\vyra.py", "source_location": "L373", "weight": 1.0}, {"source": "vyra", "target": "vyra_jarvis_bridge_post_json", "relation": "contains", "confidence": "EXTRACTED", "source_file": "backend\\vyra.py", "source_location": "L384", "weight": 1.0}, {"source": "vyra", "target": "vyra_jarvis_bridge_get_json", "relation": "contains", "confidence": "EXTRACTED", "source_file": "backend\\vyra.py", "source_location": "L395", "weight": 1.0}, {"source": "vyra", "target": "vyra_get_girlfriend_instruction", "relation": "contains", "confidence": "EXTRACTED", "source_file": "backend\\vyra.py", "source_location": "L1842", "weight": 1.0}, {"source": "vyra", "target": "vyra_get_bestfriend_instruction", "relation": "contains", "confidence": "EXTRACTED", "source_file": "backend\\vyra.py", "source_location": "L1983", "weight": 1.0}, {"source": "vyra", "target": "vyra_get_professional_instruction", "relation": "contains", "confidence": "EXTRACTED", "source_file": "backend\\vyra.py", "source_location": "L2106", "weight": 1.0}, {"source": "vyra", "target": "vyra_get_system_instruction", "relation": "contains", "confidence": "EXTRACTED", "source_file": "backend\\vyra.py", "source_location": "L2255", "weight": 1.0}, {"source": "vyra", "target": "vyra_audioloop", "relation": "contains", "confidence": "EXTRACTED", "source_file": "backend\\vyra.py", "source_location": "L2359", "weight": 1.0}, {"source": "vyra_audioloop", "target": "vyra_audioloop_init", "relation": "method", "confidence": "EXTRACTED", "source_file": "backend\\vyra.py", "source_location": "L2360", "weight": 1.0}, {"source": "vyra_audioloop", "target": "vyra_audioloop_load_environmental_settings", "relation": "method", "confidence": "EXTRACTED", "source_file": "backend\\vyra.py", "source_location": "L2541", "weight": 1.0}, {"source": "vyra_audioloop", "target": "vyra_audioloop_flush_chat", "relation": "method", "confidence": "EXTRACTED", "source_file": "backend\\vyra.py", "source_location": "L2568", "weight": 1.0}, {"source": "vyra_audioloop", "target": "vyra_audioloop_inject_live_rag_context", "relation": "method", "confidence": "EXTRACTED", "source_file": "backend\\vyra.py", "source_location": "L2580", "weight": 1.0}, {"source": "vyra_audioloop", "target": "vyra_audioloop_run_self_improvement", "relation": "method", "confidence": "EXTRACTED", "source_file": "backend\\vyra.py", "source_location": "L2637", "weight": 1.0}, {"source": "vyra_audioloop", "target": "vyra_audioloop_run_memory_extraction", "relation": "method", "confidence": "EXTRACTED", "source_file": "backend\\vyra.py", "source_location": "L2652", "weight": 1.0}, {"source": "vyra_audioloop", "target": "vyra_audioloop_set_speaker_mode", "relation": "method", "confidence": "EXTRACTED", "source_file": "backend\\vyra.py", "source_location": "L2756", "weight": 1.0}, {"source": "vyra_audioloop", "target": "vyra_audioloop_set_personality_mode", "relation": "method", "confidence": "EXTRACTED", "source_file": "backend\\vyra.py", "source_location": "L2769", "weight": 1.0}, {"source": "vyra_audioloop", "target": "vyra_audioloop_switch_mode", "relation": "method", "confidence": "EXTRACTED", "source_file": "backend\\vyra.py", "source_location": "L2822", "weight": 1.0}, {"source": "vyra_audioloop", "target": "vyra_audioloop_update_permissions", "relation": "method", "confidence": "EXTRACTED", "source_file": "backend\\vyra.py", "source_location": "L2827", "weight": 1.0}, {"source": "vyra_audioloop", "target": "vyra_audioloop_set_paused", "relation": "method", "confidence": "EXTRACTED", "source_file": "backend\\vyra.py", "source_location": "L2831", "weight": 1.0}, {"source": "vyra_audioloop", "target": "vyra_audioloop_stop", "relation": "method", "confidence": "EXTRACTED", "source_file": "backend\\vyra.py", "source_location": "L2837", "weight": 1.0}, {"source": "vyra_audioloop", "target": "vyra_audioloop_resolve_tool_confirmation", "relation": "method", "confidence": "EXTRACTED", "source_file": "backend\\vyra.py", "source_location": "L2840", "weight": 1.0}, {"source": "vyra_audioloop", "target": "vyra_audioloop_clear_audio_queue", "relation": "method", "confidence": "EXTRACTED", "source_file": "backend\\vyra.py", "source_location": "L2856", "weight": 1.0}, {"source": "vyra_audioloop", "target": "vyra_audioloop_send_frame", "relation": "method", "confidence": "EXTRACTED", "source_file": "backend\\vyra.py", "source_location": "L2875", "weight": 1.0}, {"source": "vyra_audioloop", "target": "vyra_audioloop_analyze_scene", "relation": "method", "confidence": "EXTRACTED", "source_file": "backend\\vyra.py", "source_location": "L2942", "weight": 1.0}, {"source": "vyra_audioloop", "target": "vyra_audioloop_send_realtime", "relation": "method", "confidence": "EXTRACTED", "source_file": "backend\\vyra.py", "source_location": "L2983", "weight": 1.0}, {"source": "vyra_audioloop", "target": "vyra_audioloop_check_speaker_identity", "relation": "method", "confidence": "EXTRACTED", "source_file": "backend\\vyra.py", "source_location": "L2988", "weight": 1.0}, {"source": "vyra_audioloop", "target": "vyra_audioloop_analyze_environment", "relation": "method", "confidence": "EXTRACTED", "source_file": "backend\\vyra.py", "source_location": "L3041", "weight": 1.0}, {"source": "vyra_audioloop", "target": "vyra_audioloop_listen_audio", "relation": "method", "confidence": "EXTRACTED", "source_file": "backend\\vyra.py", "source_location": "L3156", "weight": 1.0}, {"source": "vyra_audioloop", "target": "vyra_audioloop_handle_cad_request", "relation": "method", "confidence": "EXTRACTED", "source_file": "backend\\vyra.py", "source_location": "L3350", "weight": 1.0}, {"source": "vyra_audioloop", "target": "vyra_audioloop_handle_write_file", "relation": "method", "confidence": "EXTRACTED", "source_file": "backend\\vyra.py", "source_location": "L3419", "weight": 1.0}, {"source": "vyra_audioloop", "target": "vyra_audioloop_handle_read_directory", "relation": "method", "confidence": "EXTRACTED", "source_file": "backend\\vyra.py", "source_location": "L3470", "weight": 1.0}, {"source": "vyra_audioloop", "target": "vyra_audioloop_handle_read_file", "relation": "method", "confidence": "EXTRACTED", "source_file": "backend\\vyra.py", "source_location": "L3487", "weight": 1.0}, {"source": "vyra_audioloop", "target": "vyra_audioloop_handle_web_agent_request", "relation": "method", "confidence": "EXTRACTED", "source_file": "backend\\vyra.py", "source_location": "L3505", "weight": 1.0}, {"source": "vyra_audioloop", "target": "vyra_audioloop_handle_crawlee_request", "relation": "method", "confidence": "EXTRACTED", "source_file": "backend\\vyra.py", "source_location": "L3524", "weight": 1.0}, {"source": "vyra_audioloop", "target": "vyra_audioloop_receive_audio", "relation": "method", "confidence": "EXTRACTED", "source_file": "backend\\vyra.py", "source_location": "L3537", "weight": 1.0}, {"source": "vyra_audioloop", "target": "vyra_audioloop_play_audio", "relation": "method", "confidence": "EXTRACTED", "source_file": "backend\\vyra.py", "source_location": "L5572", "weight": 1.0}, {"source": "vyra_audioloop", "target": "vyra_audioloop_flush_input_buffer", "relation": "method", "confidence": "EXTRACTED", "source_file": "backend\\vyra.py", "source_location": "L5632", "weight": 1.0}, {"source": "vyra_audioloop", "target": "vyra_audioloop_session_keepalive", "relation": "method", "confidence": "EXTRACTED", "source_file": "backend\\vyra.py", "source_location": "L5642", "weight": 1.0}, {"source": "vyra_audioloop", "target": "vyra_audioloop_get_system_snapshot", "relation": "method", "confidence": "EXTRACTED", "source_file": "backend\\vyra.py", "source_location": "L5667", "weight": 1.0}, {"source": "vyra_audioloop", "target": "vyra_audioloop_proactive_loop", "relation": "method", "confidence": "EXTRACTED", "source_file": "backend\\vyra.py", "source_location": "L5696", "weight": 1.0}, {"source": "vyra_audioloop", "target": "vyra_audioloop_get_frames", "relation": "method", "confidence": "EXTRACTED", "source_file": "backend\\vyra.py", "source_location": "L5776", "weight": 1.0}, {"source": "vyra_audioloop", "target": "vyra_audioloop_get_frame", "relation": "method", "confidence": "EXTRACTED", "source_file": "backend\\vyra.py", "source_location": "L5798", "weight": 1.0}, {"source": "vyra_audioloop", "target": "vyra_audioloop_get_screen", "relation": "method", "confidence": "EXTRACTED", "source_file": "backend\\vyra.py", "source_location": "L5811", "weight": 1.0}, {"source": "vyra_audioloop", "target": "vyra_audioloop_get_screen", "relation": "method", "confidence": "EXTRACTED", "source_file": "backend\\vyra.py", "source_location": "L5814", "weight": 1.0}, {"source": "vyra_audioloop", "target": "vyra_audioloop_run", "relation": "method", "confidence": "EXTRACTED", "source_file": "backend\\vyra.py", "source_location": "L5817", "weight": 1.0}, {"source": "vyra", "target": "vyra_get_input_devices", "relation": "contains", "confidence": "EXTRACTED", "source_file": "backend\\vyra.py", "source_location": "L6312", "weight": 1.0}, {"source": "vyra", "target": "vyra_get_output_devices", "relation": "contains", "confidence": "EXTRACTED", "source_file": "backend\\vyra.py", "source_location": "L6325", "weight": 1.0}, {"source": "vyra_get_system_instruction", "target": "vyra_build_user_memory_block", "relation": "calls", "confidence": "EXTRACTED", "source_file": "backend\\vyra.py", "source_location": "L2280", "weight": 1.0}, {"source": "vyra_get_system_instruction", "target": "vyra_get_girlfriend_instruction", "relation": "calls", "confidence": "EXTRACTED", "source_file": "backend\\vyra.py", "source_location": "L2297", "weight": 1.0}, {"source": "vyra_get_system_instruction", "target": "vyra_get_professional_instruction", "relation": "calls", "confidence": "EXTRACTED", "source_file": "backend\\vyra.py", "source_location": "L2299", "weight": 1.0}, {"source": "vyra_get_system_instruction", "target": "vyra_get_bestfriend_instruction", "relation": "calls", "confidence": "EXTRACTED", "source_file": "backend\\vyra.py", "source_location": "L2301", "weight": 1.0}, {"source": "vyra_audioloop_init", "target": "vyra_audioloop_load_environmental_settings", "relation": "calls", "confidence": "EXTRACTED", "source_file": "backend\\vyra.py", "source_location": "L2522", "weight": 1.0}, {"source": "vyra_audioloop_run_memory_extraction", "target": "vyra_build_user_memory_block", "relation": "calls", "confidence": "EXTRACTED", "source_file": "backend\\vyra.py", "source_location": "L2737", "weight": 1.0}, {"source": "vyra_audioloop_set_personality_mode", "target": "vyra_get_system_instruction", "relation": "calls", "confidence": "EXTRACTED", "source_file": "backend\\vyra.py", "source_location": "L2786", "weight": 1.0}, {"source": "vyra_audioloop_switch_mode", "target": "vyra_audioloop_set_personality_mode", "relation": "calls", "confidence": "EXTRACTED", "source_file": "backend\\vyra.py", "source_location": "L2825", "weight": 1.0}, {"source": "vyra_audioloop_send_frame", "target": "vyra_audioloop_analyze_scene", "relation": "calls", "confidence": "EXTRACTED", "source_file": "backend\\vyra.py", "source_location": "L2940", "weight": 1.0}, {"source": "vyra_audioloop_check_speaker_identity", "target": "vyra_audioloop_set_speaker_mode", "relation": "calls", "confidence": "EXTRACTED", "source_file": "backend\\vyra.py", "source_location": "L3019", "weight": 1.0}, {"source": "vyra_audioloop_listen_audio", "target": "vyra_audioloop_check_speaker_identity", "relation": "calls", "confidence": "EXTRACTED", "source_file": "backend\\vyra.py", "source_location": "L3291", "weight": 1.0}, {"source": "vyra_audioloop_listen_audio", "target": "vyra_audioloop_analyze_environment", "relation": "calls", "confidence": "EXTRACTED", "source_file": "backend\\vyra.py", "source_location": "L3303", "weight": 1.0}, {"source": "vyra_audioloop_receive_audio", "target": "vyra_audioloop_clear_audio_queue", "relation": "calls", "confidence": "EXTRACTED", "source_file": "backend\\vyra.py", "source_location": "L3588", "weight": 1.0}, {"source": "vyra_audioloop_receive_audio", "target": "vyra_audioloop_handle_cad_request", "relation": "calls", "confidence": "EXTRACTED", "source_file": "backend\\vyra.py", "source_location": "L3787", "weight": 1.0}, {"source": "vyra_audioloop_receive_audio", "target": "vyra_audioloop_handle_web_agent_request", "relation": "calls", "confidence": "EXTRACTED", "source_file": "backend\\vyra.py", "source_location": "L3794", "weight": 1.0}, {"source": "vyra_audioloop_receive_audio", "target": "vyra_audioloop_handle_crawlee_request", "relation": "calls", "confidence": "EXTRACTED", "source_file": "backend\\vyra.py", "source_location": "L3816", "weight": 1.0}, {"source": "vyra_audioloop_receive_audio", "target": "vyra_audioloop_handle_write_file", "relation": "calls", "confidence": "EXTRACTED", "source_file": "backend\\vyra.py", "source_location": "L3973", "weight": 1.0}, {"source": "vyra_audioloop_receive_audio", "target": "vyra_audioloop_handle_read_directory", "relation": "calls", "confidence": "EXTRACTED", "source_file": "backend\\vyra.py", "source_location": "L3986", "weight": 1.0}, {"source": "vyra_audioloop_receive_audio", "target": "vyra_audioloop_handle_read_file", "relation": "calls", "confidence": "EXTRACTED", "source_file": "backend\\vyra.py", "source_location": "L3999", "weight": 1.0}, {"source": "vyra_audioloop_receive_audio", "target": "vyra_audioloop_set_personality_mode", "relation": "calls", "confidence": "EXTRACTED", "source_file": "backend\\vyra.py", "source_location": "L4058", "weight": 1.0}, {"source": "vyra_audioloop_receive_audio", "target": "vyra_call_jarvis_chat_via_ws", "relation": "calls", "confidence": "EXTRACTED", "source_file": "backend\\vyra.py", "source_location": "L4810", "weight": 1.0}, {"source": "vyra_audioloop_receive_audio", "target": "vyra_jarvis_vault_get_json", "relation": "calls", "confidence": "EXTRACTED", "source_file": "backend\\vyra.py", "source_location": "L4837", "weight": 1.0}, {"source": "vyra_audioloop_receive_audio", "target": "vyra_jarvis_vault_post_json", "relation": "calls", "confidence": "EXTRACTED", "source_file": "backend\\vyra.py", "source_location": "L4871", "weight": 1.0}, {"source": "vyra_audioloop_receive_audio", "target": "vyra_jarvis_bridge_get_json", "relation": "calls", "confidence": "EXTRACTED", "source_file": "backend\\vyra.py", "source_location": "L4886", "weight": 1.0}, {"source": "vyra_audioloop_receive_audio", "target": "vyra_build_user_memory_block", "relation": "calls", "confidence": "EXTRACTED", "source_file": "backend\\vyra.py", "source_location": "L5488", "weight": 1.0}, {"source": "vyra_audioloop_receive_audio", "target": "vyra_audioloop_flush_chat", "relation": "calls", "confidence": "EXTRACTED", "source_file": "backend\\vyra.py", "source_location": "L5492", "weight": 1.0}, {"source": "vyra_audioloop_receive_audio", "target": "vyra_audioloop_run_memory_extraction", "relation": "calls", "confidence": "EXTRACTED", "source_file": "backend\\vyra.py", "source_location": "L5504", "weight": 1.0}, {"source": "vyra_audioloop_receive_audio", "target": "vyra_audioloop_run_self_improvement", "relation": "calls", "confidence": "EXTRACTED", "source_file": "backend\\vyra.py", "source_location": "L5508", "weight": 1.0}, {"source": "vyra_audioloop_receive_audio", "target": "vyra_audioloop_inject_live_rag_context", "relation": "calls", "confidence": "EXTRACTED", "source_file": "backend\\vyra.py", "source_location": "L5557", "weight": 1.0}, {"source": "vyra_audioloop_get_frames", "target": "vyra_audioloop_stop", "relation": "calls", "confidence": "EXTRACTED", "source_file": "backend\\vyra.py", "source_location": "L5796", "weight": 1.0}, {"source": "vyra_audioloop_run", "target": "vyra_audioloop_send_realtime", "relation": "calls", "confidence": "EXTRACTED", "source_file": "backend\\vyra.py", "source_location": "L6035", "weight": 1.0}, {"source": "vyra_audioloop_run", "target": "vyra_audioloop_listen_audio", "relation": "calls", "confidence": "EXTRACTED", "source_file": "backend\\vyra.py", "source_location": "L6036", "weight": 1.0}, {"source": "vyra_audioloop_run", "target": "vyra_audioloop_get_frames", "relation": "calls", "confidence": "EXTRACTED", "source_file": "backend\\vyra.py", "source_location": "L6040", "weight": 1.0}, {"source": "vyra_audioloop_run", "target": "vyra_audioloop_receive_audio", "relation": "calls", "confidence": "EXTRACTED", "source_file": "backend\\vyra.py", "source_location": "L6044", "weight": 1.0}, {"source": "vyra_audioloop_run", "target": "vyra_audioloop_play_audio", "relation": "calls", "confidence": "EXTRACTED", "source_file": "backend\\vyra.py", "source_location": "L6045", "weight": 1.0}, {"source": "vyra_audioloop_run", "target": "vyra_audioloop_session_keepalive", "relation": "calls", "confidence": "EXTRACTED", "source_file": "backend\\vyra.py", "source_location": "L6047", "weight": 1.0}, {"source": "vyra_audioloop_run", "target": "vyra_audioloop_proactive_loop", "relation": "calls", "confidence": "EXTRACTED", "source_file": "backend\\vyra.py", "source_location": "L6049", "weight": 1.0}, {"source": "vyra_audioloop_run", "target": "vyra_audioloop_get_system_snapshot", "relation": "calls", "confidence": "EXTRACTED", "source_file": "backend\\vyra.py", "source_location": "L6081", "weight": 1.0}, {"source": "vyra_rationale_161", "target": "vyra_build_user_memory_block", "relation": "rationale_for", "confidence": "EXTRACTED", "source_file": "backend\\vyra.py", "source_location": "L161", "weight": 1.0}, {"source": "vyra_rationale_303", "target": "vyra_call_jarvis_chat_via_ws", "relation": "rationale_for", "confidence": "EXTRACTED", "source_file": "backend\\vyra.py", "source_location": "L303", "weight": 1.0}, {"source": "vyra_rationale_1843", "target": "vyra_get_girlfriend_instruction", "relation": "rationale_for", "confidence": "EXTRACTED", "source_file": "backend\\vyra.py", "source_location": "L1843", "weight": 1.0}, {"source": "vyra_rationale_1984", "target": "vyra_get_bestfriend_instruction", "relation": "rationale_for", "confidence": "EXTRACTED", "source_file": "backend\\vyra.py", "source_location": "L1984", "weight": 1.0}, {"source": "vyra_rationale_2107", "target": "vyra_get_professional_instruction", "relation": "rationale_for", "confidence": "EXTRACTED", "source_file": "backend\\vyra.py", "source_location": "L2107", "weight": 1.0}, {"source": "vyra_rationale_2256", "target": "vyra_get_system_instruction", "relation": "rationale_for", "confidence": "EXTRACTED", "source_file": "backend\\vyra.py", "source_location": "L2256", "weight": 1.0}, {"source": "vyra_rationale_2542", "target": "vyra_audioloop_load_environmental_settings", "relation": "rationale_for", "confidence": "EXTRACTED", "source_file": "backend\\vyra.py", "source_location": "L2542", "weight": 1.0}, {"source": "vyra_rationale_2569", "target": "vyra_audioloop_flush_chat", "relation": "rationale_for", "confidence": "EXTRACTED", "source_file": "backend\\vyra.py", "source_location": "L2569", "weight": 1.0}, {"source": "vyra_rationale_2581", "target": "vyra_audioloop_inject_live_rag_context", "relation": "rationale_for", "confidence": "EXTRACTED", "source_file": "backend\\vyra.py", "source_location": "L2581", "weight": 1.0}, {"source": "vyra_rationale_2638", "target": "vyra_audioloop_run_self_improvement", "relation": "rationale_for", "confidence": "EXTRACTED", "source_file": "backend\\vyra.py", "source_location": "L2638", "weight": 1.0}, {"source": "vyra_rationale_2653", "target": "vyra_audioloop_run_memory_extraction", "relation": "rationale_for", "confidence": "EXTRACTED", "source_file": "backend\\vyra.py", "source_location": "L2653", "weight": 1.0}, {"source": "vyra_rationale_2757", "target": "vyra_audioloop_set_speaker_mode", "relation": "rationale_for", "confidence": "EXTRACTED", "source_file": "backend\\vyra.py", "source_location": "L2757", "weight": 1.0}, {"source": "vyra_rationale_2770", "target": "vyra_audioloop_set_personality_mode", "relation": "rationale_for", "confidence": "EXTRACTED", "source_file": "backend\\vyra.py", "source_location": "L2770", "weight": 1.0}, {"source": "vyra_rationale_2823", "target": "vyra_audioloop_switch_mode", "relation": "rationale_for", "confidence": "EXTRACTED", "source_file": "backend\\vyra.py", "source_location": "L2823", "weight": 1.0}, {"source": "vyra_rationale_2857", "target": "vyra_audioloop_clear_audio_queue", "relation": "rationale_for", "confidence": "EXTRACTED", "source_file": "backend\\vyra.py", "source_location": "L2857", "weight": 1.0}, {"source": "vyra_rationale_2943", "target": "vyra_audioloop_analyze_scene", "relation": "rationale_for", "confidence": "EXTRACTED", "source_file": "backend\\vyra.py", "source_location": "L2943", "weight": 1.0}, {"source": "vyra_rationale_2989", "target": "vyra_audioloop_check_speaker_identity", "relation": "rationale_for", "confidence": "EXTRACTED", "source_file": "backend\\vyra.py", "source_location": "L2989", "weight": 1.0}, {"source": "vyra_rationale_3042", "target": "vyra_audioloop_analyze_environment", "relation": "rationale_for", "confidence": "EXTRACTED", "source_file": "backend\\vyra.py", "source_location": "L3042", "weight": 1.0}, {"source": "vyra_rationale_3538", "target": "vyra_audioloop_receive_audio", "relation": "rationale_for", "confidence": "EXTRACTED", "source_file": "backend\\vyra.py", "source_location": "L3538", "weight": 1.0}, {"source": "vyra_rationale_5633", "target": "vyra_audioloop_flush_input_buffer", "relation": "rationale_for", "confidence": "EXTRACTED", "source_file": "backend\\vyra.py", "source_location": "L5633", "weight": 1.0}, {"source": "vyra_rationale_5643", "target": "vyra_audioloop_session_keepalive", "relation": "rationale_for", "confidence": "EXTRACTED", "source_file": "backend\\vyra.py", "source_location": "L5643", "weight": 1.0}, {"source": "vyra_rationale_5668", "target": "vyra_audioloop_get_system_snapshot", "relation": "rationale_for", "confidence": "EXTRACTED", "source_file": "backend\\vyra.py", "source_location": "L5668", "weight": 1.0}, {"source": "vyra_rationale_5697", "target": "vyra_audioloop_proactive_loop", "relation": "rationale_for", "confidence": "EXTRACTED", "source_file": "backend\\vyra.py", "source_location": "L5697", "weight": 1.0}, {"source": "vyra_rationale_3089", "target": "vyra", "relation": "rationale_for", "confidence": "EXTRACTED", "source_file": "backend\\vyra.py", "source_location": "L3089", "weight": 1.0}, {"source": "vyra_rationale_3555", "target": "vyra", "relation": "rationale_for", "confidence": "EXTRACTED", "source_file": "backend\\vyra.py", "source_location": "L3555", "weight": 1.0}]}