{"nodes": [{"id": "desktop_darwin", "label": "desktop_darwin.go", "file_type": "code", "source_file": "jarvis\\sidecar\\desktop_darwin.go", "source_location": "L1"}, {"id": "desktop_darwin_handlelistwindows", "label": "handleListWindows()", "file_type": "code", "source_file": "jarvis\\sidecar\\desktop_darwin.go", "source_location": "L29"}, {"id": "desktop_darwin_handlegetwindowtree", "label": "handleGetWindowTree()", "file_type": "code", "source_file": "jarvis\\sidecar\\desktop_darwin.go", "source_location": "L90"}, {"id": "desktop_darwin_handleclickelement", "label": "handleClickElement()", "file_type": "code", "source_file": "jarvis\\sidecar\\desktop_darwin.go", "source_location": "L186"}, {"id": "desktop_darwin_clickatcoords", "label": "clickAtCoords()", "file_type": "code", "source_file": "jarvis\\sidecar\\desktop_darwin.go", "source_location": "L241"}, {"id": "desktop_darwin_handletypetext", "label": "handleTypeText()", "file_type": "code", "source_file": "jarvis\\sidecar\\desktop_darwin.go", "source_location": "L268"}, {"id": "desktop_darwin_handlepresskeys", "label": "handlePressKeys()", "file_type": "code", "source_file": "jarvis\\sidecar\\desktop_darwin.go", "source_location": "L296"}, {"id": "desktop_darwin_handlelaunchapp", "label": "handleLaunchApp()", "file_type": "code", "source_file": "jarvis\\sidecar\\desktop_darwin.go", "source_location": "L312"}, {"id": "desktop_darwin_handlefocuswindow", "label": "handleFocusWindow()", "file_type": "code", "source_file": "jarvis\\sidecar\\desktop_darwin.go", "source_location": "L379"}, {"id": "desktop_darwin_doubleclickatcoords", "label": "doubleClickAtCoords()", "file_type": "code", "source_file": "jarvis\\sidecar\\desktop_darwin.go", "source_location": "L399"}, {"id": "desktop_darwin_rightclickatcoords", "label": "rightClickAtCoords()", "file_type": "code", "source_file": "jarvis\\sidecar\\desktop_darwin.go", "source_location": "L424"}, {"id": "desktop_darwin_handlefindelement", "label": "handleFindElement()", "file_type": "code", "source_file": "jarvis\\sidecar\\desktop_darwin.go", "source_location": "L447"}, {"id": "desktop_darwin_runosascript", "label": "runOsascript()", "file_type": "code", "source_file": "jarvis\\sidecar\\desktop_darwin.go", "source_location": "L494"}, {"id": "desktop_darwin_runosascriptjs", "label": "runOsascriptJS()", "file_type": "code", "source_file": "jarvis\\sidecar\\desktop_darwin.go", "source_location": "L506"}, {"id": "desktop_darwin_convertkeystoosascript", "label": "convertKeysToOsascript()", "file_type": "code", "source_file": "jarvis\\sidecar\\desktop_darwin.go", "source_location": "L522"}, {"id": "desktop_darwin_osascriptkeycode", "label": "osascriptKeyCode()", "file_type": "code", "source_file": "jarvis\\sidecar\\desktop_darwin.go", "source_location": "L571"}, {"id": "desktop_darwin_toint", "label": "toInt()", "file_type": "code", "source_file": "jarvis\\sidecar\\desktop_darwin.go", "source_location": "L611"}], "edges": [{"source": "desktop_darwin", "target": "context", "relation": "imports_from", "confidence": "EXTRACTED", "source_file": "jarvis\\sidecar\\desktop_darwin.go", "source_location": "L6", "weight": 1.0}, {"source": "desktop_darwin", "target": "json", "relation": "imports_from", "confidence": "EXTRACTED", "source_file": "jarvis\\sidecar\\desktop_darwin.go", "source_location": "L7", "weight": 1.0}, {"source": "desktop_darwin", "target": "fmt", "relation": "imports_from", "confidence": "EXTRACTED", "source_file": "jarvis\\sidecar\\desktop_darwin.go", "source_location": "L8", "weight": 1.0}, {"source": "desktop_darwin", "target": "exec", "relation": "imports_from", "confidence": "EXTRACTED", "source_file": "jarvis\\sidecar\\desktop_darwin.go", "source_location": "L9", "weight": 1.0}, {"source": "desktop_darwin", "target": "strconv", "relation": "imports_from", "confidence": "EXTRACTED", "source_file": "jarvis\\sidecar\\desktop_darwin.go", "source_location": "L10", "weight": 1.0}, {"source": "desktop_darwin", "target": "strings", "relation": "imports_from", "confidence": "EXTRACTED", "source_file": "jarvis\\sidecar\\desktop_darwin.go", "source_location": "L11", "weight": 1.0}, {"source": "desktop_darwin", "target": "sync", "relation": "imports_from", "confidence": "EXTRACTED", "source_file": "jarvis\\sidecar\\desktop_darwin.go", "source_location": "L12", "weight": 1.0}, {"source": "desktop_darwin", "target": "time", "relation": "imports_from", "confidence": "EXTRACTED", "source_file": "jarvis\\sidecar\\desktop_darwin.go", "source_location": "L13", "weight": 1.0}, {"source": "desktop_darwin", "target": "desktop_darwin_handlelistwindows", "relation": "contains", "confidence": "EXTRACTED", "source_file": "jarvis\\sidecar\\desktop_darwin.go", "source_location": "L29", "weight": 1.0}, {"source": "desktop_darwin", "target": "desktop_darwin_handlegetwindowtree", "relation": "contains", "confidence": "EXTRACTED", "source_file": "jarvis\\sidecar\\desktop_darwin.go", "source_location": "L90", "weight": 1.0}, {"source": "desktop_darwin", "target": "desktop_darwin_handleclickelement", "relation": "contains", "confidence": "EXTRACTED", "source_file": "jarvis\\sidecar\\desktop_darwin.go", "source_location": "L186", "weight": 1.0}, {"source": "desktop_darwin", "target": "desktop_darwin_clickatcoords", "relation": "contains", "confidence": "EXTRACTED", "source_file": "jarvis\\sidecar\\desktop_darwin.go", "source_location": "L241", "weight": 1.0}, {"source": "desktop_darwin", "target": "desktop_darwin_handletypetext", "relation": "contains", "confidence": "EXTRACTED", "source_file": "jarvis\\sidecar\\desktop_darwin.go", "source_location": "L268", "weight": 1.0}, {"source": "desktop_darwin", "target": "desktop_darwin_handlepresskeys", "relation": "contains", "confidence": "EXTRACTED", "source_file": "jarvis\\sidecar\\desktop_darwin.go", "source_location": "L296", "weight": 1.0}, {"source": "desktop_darwin", "target": "desktop_darwin_handlelaunchapp", "relation": "contains", "confidence": "EXTRACTED", "source_file": "jarvis\\sidecar\\desktop_darwin.go", "source_location": "L312", "weight": 1.0}, {"source": "desktop_darwin", "target": "desktop_darwin_handlefocuswindow", "relation": "contains", "confidence": "EXTRACTED", "source_file": "jarvis\\sidecar\\desktop_darwin.go", "source_location": "L379", "weight": 1.0}, {"source": "desktop_darwin", "target": "desktop_darwin_doubleclickatcoords", "relation": "contains", "confidence": "EXTRACTED", "source_file": "jarvis\\sidecar\\desktop_darwin.go", "source_location": "L399", "weight": 1.0}, {"source": "desktop_darwin", "target": "desktop_darwin_rightclickatcoords", "relation": "contains", "confidence": "EXTRACTED", "source_file": "jarvis\\sidecar\\desktop_darwin.go", "source_location": "L424", "weight": 1.0}, {"source": "desktop_darwin", "target": "desktop_darwin_handlefindelement", "relation": "contains", "confidence": "EXTRACTED", "source_file": "jarvis\\sidecar\\desktop_darwin.go", "source_location": "L447", "weight": 1.0}, {"source": "desktop_darwin", "target": "desktop_darwin_runosascript", "relation": "contains", "confidence": "EXTRACTED", "source_file": "jarvis\\sidecar\\desktop_darwin.go", "source_location": "L494", "weight": 1.0}, {"source": "desktop_darwin", "target": "desktop_darwin_runosascriptjs", "relation": "contains", "confidence": "EXTRACTED", "source_file": "jarvis\\sidecar\\desktop_darwin.go", "source_location": "L506", "weight": 1.0}, {"source": "desktop_darwin", "target": "desktop_darwin_convertkeystoosascript", "relation": "contains", "confidence": "EXTRACTED", "source_file": "jarvis\\sidecar\\desktop_darwin.go", "source_location": "L522", "weight": 1.0}, {"source": "desktop_darwin", "target": "desktop_darwin_osascriptkeycode", "relation": "contains", "confidence": "EXTRACTED", "source_file": "jarvis\\sidecar\\desktop_darwin.go", "source_location": "L571", "weight": 1.0}, {"source": "desktop_darwin", "target": "desktop_darwin_toint", "relation": "contains", "confidence": "EXTRACTED", "source_file": "jarvis\\sidecar\\desktop_darwin.go", "source_location": "L611", "weight": 1.0}, {"source": "desktop_darwin_handlelistwindows", "target": "desktop_darwin_runosascript", "relation": "calls", "confidence": "EXTRACTED", "source_file": "jarvis\\sidecar\\desktop_darwin.go", "source_location": "L49", "weight": 1.0}, {"source": "desktop_darwin_handlegetwindowtree", "target": "desktop_darwin_runosascript", "relation": "calls", "confidence": "EXTRACTED", "source_file": "jarvis\\sidecar\\desktop_darwin.go", "source_location": "L99", "weight": 1.0}, {"source": "desktop_darwin_handlegetwindowtree", "target": "desktop_darwin_runosascriptjs", "relation": "calls", "confidence": "EXTRACTED", "source_file": "jarvis\\sidecar\\desktop_darwin.go", "source_location": "L157", "weight": 1.0}, {"source": "desktop_darwin_handleclickelement", "target": "desktop_darwin_toint", "relation": "calls", "confidence": "EXTRACTED", "source_file": "jarvis\\sidecar\\desktop_darwin.go", "source_location": "L212", "weight": 1.0}, {"source": "desktop_darwin_handleclickelement", "target": "desktop_darwin_clickatcoords", "relation": "calls", "confidence": "EXTRACTED", "source_file": "jarvis\\sidecar\\desktop_darwin.go", "source_location": "L217", "weight": 1.0}, {"source": "desktop_darwin_handleclickelement", "target": "desktop_darwin_doubleclickatcoords", "relation": "calls", "confidence": "EXTRACTED", "source_file": "jarvis\\sidecar\\desktop_darwin.go", "source_location": "L221", "weight": 1.0}, {"source": "desktop_darwin_handleclickelement", "target": "desktop_darwin_rightclickatcoords", "relation": "calls", "confidence": "EXTRACTED", "source_file": "jarvis\\sidecar\\desktop_darwin.go", "source_location": "L225", "weight": 1.0}, {"source": "desktop_darwin_handletypetext", "target": "desktop_darwin_handleclickelement", "relation": "calls", "confidence": "EXTRACTED", "source_file": "jarvis\\sidecar\\desktop_darwin.go", "source_location": "L276", "weight": 1.0}, {"source": "desktop_darwin_handletypetext", "target": "desktop_darwin_runosascript", "relation": "calls", "confidence": "EXTRACTED", "source_file": "jarvis\\sidecar\\desktop_darwin.go", "source_location": "L287", "weight": 1.0}, {"source": "desktop_darwin_handlepresskeys", "target": "desktop_darwin_convertkeystoosascript", "relation": "calls", "confidence": "EXTRACTED", "source_file": "jarvis\\sidecar\\desktop_darwin.go", "source_location": "L302", "weight": 1.0}, {"source": "desktop_darwin_handlepresskeys", "target": "desktop_darwin_runosascript", "relation": "calls", "confidence": "EXTRACTED", "source_file": "jarvis\\sidecar\\desktop_darwin.go", "source_location": "L303", "weight": 1.0}, {"source": "desktop_darwin_handlefocuswindow", "target": "desktop_darwin_runosascript", "relation": "calls", "confidence": "EXTRACTED", "source_file": "jarvis\\sidecar\\desktop_darwin.go", "source_location": "L392", "weight": 1.0}, {"source": "desktop_darwin_handlefindelement", "target": "desktop_darwin_handlegetwindowtree", "relation": "calls", "confidence": "EXTRACTED", "source_file": "jarvis\\sidecar\\desktop_darwin.go", "source_location": "L449", "weight": 1.0}, {"source": "desktop_darwin_convertkeystoosascript", "target": "desktop_darwin_osascriptkeycode", "relation": "calls", "confidence": "EXTRACTED", "source_file": "jarvis\\sidecar\\desktop_darwin.go", "source_location": "L559", "weight": 1.0}]}