{"nodes": [{"id": "docs_comments_test", "label": "docs_comments_test.go", "file_type": "code", "source_file": "gogcli\\internal\\cmd\\docs_comments_test.go", "source_location": "L1"}, {"id": "docs_comments_test_newcommentstestserver", "label": "newCommentsTestServer()", "file_type": "code", "source_file": "gogcli\\internal\\cmd\\docs_comments_test.go", "source_location": "L20"}, {"id": "docs_comments_test_setupdriveservicefromserver", "label": "setupDriveServiceFromServer()", "file_type": "code", "source_file": "gogcli\\internal\\cmd\\docs_comments_test.go", "source_location": "L173"}, {"id": "docs_comments_test_testdocscommentslist_filtersresolved", "label": "TestDocsCommentsList_FiltersResolved()", "file_type": "code", "source_file": "gogcli\\internal\\cmd\\docs_comments_test.go", "source_location": "L189"}, {"id": "docs_comments_test_testdocscommentslist_includeresolved", "label": "TestDocsCommentsList_IncludeResolved()", "file_type": "code", "source_file": "gogcli\\internal\\cmd\\docs_comments_test.go", "source_location": "L222"}, {"id": "docs_comments_test_testdocscommentslist_plaintext", "label": "TestDocsCommentsList_PlainText()", "file_type": "code", "source_file": "gogcli\\internal\\cmd\\docs_comments_test.go", "source_location": "L246"}, {"id": "docs_comments_test_testdocscommentslist_scanspagesforopencomments", "label": "TestDocsCommentsList_ScansPagesForOpenComments()", "file_type": "code", "source_file": "gogcli\\internal\\cmd\\docs_comments_test.go", "source_location": "L276"}, {"id": "docs_comments_test_testdocscommentslist_empty", "label": "TestDocsCommentsList_Empty()", "file_type": "code", "source_file": "gogcli\\internal\\cmd\\docs_comments_test.go", "source_location": "L300"}, {"id": "docs_comments_test_testdocscommentsget_json", "label": "TestDocsCommentsGet_JSON()", "file_type": "code", "source_file": "gogcli\\internal\\cmd\\docs_comments_test.go", "source_location": "L315"}, {"id": "docs_comments_test_testdocscommentsget_plain", "label": "TestDocsCommentsGet_Plain()", "file_type": "code", "source_file": "gogcli\\internal\\cmd\\docs_comments_test.go", "source_location": "L342"}, {"id": "docs_comments_test_testdocscommentsadd_json", "label": "TestDocsCommentsAdd_JSON()", "file_type": "code", "source_file": "gogcli\\internal\\cmd\\docs_comments_test.go", "source_location": "L368"}, {"id": "docs_comments_test_testdocscommentsadd_plain", "label": "TestDocsCommentsAdd_Plain()", "file_type": "code", "source_file": "gogcli\\internal\\cmd\\docs_comments_test.go", "source_location": "L398"}, {"id": "docs_comments_test_testdocscommentsreply_json", "label": "TestDocsCommentsReply_JSON()", "file_type": "code", "source_file": "gogcli\\internal\\cmd\\docs_comments_test.go", "source_location": "L415"}, {"id": "docs_comments_test_testdocscommentsresolve_json", "label": "TestDocsCommentsResolve_JSON()", "file_type": "code", "source_file": "gogcli\\internal\\cmd\\docs_comments_test.go", "source_location": "L439"}, {"id": "docs_comments_test_testdocscommentsdelete_json", "label": "TestDocsCommentsDelete_JSON()", "file_type": "code", "source_file": "gogcli\\internal\\cmd\\docs_comments_test.go", "source_location": "L465"}, {"id": "docs_comments_test_testdocscomments_validationerrors", "label": "TestDocsComments_ValidationErrors()", "file_type": "code", "source_file": "gogcli\\internal\\cmd\\docs_comments_test.go", "source_location": "L491"}, {"id": "docs_comments_test_testfilteropencomments", "label": "TestFilterOpenComments()", "file_type": "code", "source_file": "gogcli\\internal\\cmd\\docs_comments_test.go", "source_location": "L537"}, {"id": "docs_comments_test_testfilteropencomments_allopen", "label": "TestFilterOpenComments_AllOpen()", "file_type": "code", "source_file": "gogcli\\internal\\cmd\\docs_comments_test.go", "source_location": "L553"}, {"id": "docs_comments_test_testfilteropencomments_allresolved", "label": "TestFilterOpenComments_AllResolved()", "file_type": "code", "source_file": "gogcli\\internal\\cmd\\docs_comments_test.go", "source_location": "L563"}, {"id": "docs_comments_test_testfilteropencomments_nil", "label": "TestFilterOpenComments_Nil()", "file_type": "code", "source_file": "gogcli\\internal\\cmd\\docs_comments_test.go", "source_location": "L573"}, {"id": "docs_comments_test_testfilteropencomments_nilelements", "label": "TestFilterOpenComments_NilElements()", "file_type": "code", "source_file": "gogcli\\internal\\cmd\\docs_comments_test.go", "source_location": "L580"}], "edges": [{"source": "docs_comments_test", "target": "context", "relation": "imports_from", "confidence": "EXTRACTED", "source_file": "gogcli\\internal\\cmd\\docs_comments_test.go", "source_location": "L4", "weight": 1.0}, {"source": "docs_comments_test", "target": "json", "relation": "imports_from", "confidence": "EXTRACTED", "source_file": "gogcli\\internal\\cmd\\docs_comments_test.go", "source_location": "L5", "weight": 1.0}, {"source": "docs_comments_test", "target": "io", "relation": "imports_from", "confidence": "EXTRACTED", "source_file": "gogcli\\internal\\cmd\\docs_comments_test.go", "source_location": "L6", "weight": 1.0}, {"source": "docs_comments_test", "target": "http", "relation": "imports_from", "confidence": "EXTRACTED", "source_file": "gogcli\\internal\\cmd\\docs_comments_test.go", "source_location": "L7", "weight": 1.0}, {"source": "docs_comments_test", "target": "httptest", "relation": "imports_from", "confidence": "EXTRACTED", "source_file": "gogcli\\internal\\cmd\\docs_comments_test.go", "source_location": "L8", "weight": 1.0}, {"source": "docs_comments_test", "target": "strings", "relation": "imports_from", "confidence": "EXTRACTED", "source_file": "gogcli\\internal\\cmd\\docs_comments_test.go", "source_location": "L9", "weight": 1.0}, {"source": "docs_comments_test", "target": "testing", "relation": "imports_from", "confidence": "EXTRACTED", "source_file": "gogcli\\internal\\cmd\\docs_comments_test.go", "source_location": "L10", "weight": 1.0}, {"source": "docs_comments_test", "target": "v3", "relation": "imports_from", "confidence": "EXTRACTED", "source_file": "gogcli\\internal\\cmd\\docs_comments_test.go", "source_location": "L12", "weight": 1.0}, {"source": "docs_comments_test", "target": "option", "relation": "imports_from", "confidence": "EXTRACTED", "source_file": "gogcli\\internal\\cmd\\docs_comments_test.go", "source_location": "L13", "weight": 1.0}, {"source": "docs_comments_test", "target": "ui", "relation": "imports_from", "confidence": "EXTRACTED", "source_file": "gogcli\\internal\\cmd\\docs_comments_test.go", "source_location": "L15", "weight": 1.0}, {"source": "docs_comments_test", "target": "docs_comments_test_newcommentstestserver", "relation": "contains", "confidence": "EXTRACTED", "source_file": "gogcli\\internal\\cmd\\docs_comments_test.go", "source_location": "L20", "weight": 1.0}, {"source": "docs_comments_test", "target": "docs_comments_test_setupdriveservicefromserver", "relation": "contains", "confidence": "EXTRACTED", "source_file": "gogcli\\internal\\cmd\\docs_comments_test.go", "source_location": "L173", "weight": 1.0}, {"source": "docs_comments_test", "target": "docs_comments_test_testdocscommentslist_filtersresolved", "relation": "contains", "confidence": "EXTRACTED", "source_file": "gogcli\\internal\\cmd\\docs_comments_test.go", "source_location": "L189", "weight": 1.0}, {"source": "docs_comments_test", "target": "docs_comments_test_testdocscommentslist_includeresolved", "relation": "contains", "confidence": "EXTRACTED", "source_file": "gogcli\\internal\\cmd\\docs_comments_test.go", "source_location": "L222", "weight": 1.0}, {"source": "docs_comments_test", "target": "docs_comments_test_testdocscommentslist_plaintext", "relation": "contains", "confidence": "EXTRACTED", "source_file": "gogcli\\internal\\cmd\\docs_comments_test.go", "source_location": "L246", "weight": 1.0}, {"source": "docs_comments_test", "target": "docs_comments_test_testdocscommentslist_scanspagesforopencomments", "relation": "contains", "confidence": "EXTRACTED", "source_file": "gogcli\\internal\\cmd\\docs_comments_test.go", "source_location": "L276", "weight": 1.0}, {"source": "docs_comments_test", "target": "docs_comments_test_testdocscommentslist_empty", "relation": "contains", "confidence": "EXTRACTED", "source_file": "gogcli\\internal\\cmd\\docs_comments_test.go", "source_location": "L300", "weight": 1.0}, {"source": "docs_comments_test", "target": "docs_comments_test_testdocscommentsget_json", "relation": "contains", "confidence": "EXTRACTED", "source_file": "gogcli\\internal\\cmd\\docs_comments_test.go", "source_location": "L315", "weight": 1.0}, {"source": "docs_comments_test", "target": "docs_comments_test_testdocscommentsget_plain", "relation": "contains", "confidence": "EXTRACTED", "source_file": "gogcli\\internal\\cmd\\docs_comments_test.go", "source_location": "L342", "weight": 1.0}, {"source": "docs_comments_test", "target": "docs_comments_test_testdocscommentsadd_json", "relation": "contains", "confidence": "EXTRACTED", "source_file": "gogcli\\internal\\cmd\\docs_comments_test.go", "source_location": "L368", "weight": 1.0}, {"source": "docs_comments_test", "target": "docs_comments_test_testdocscommentsadd_plain", "relation": "contains", "confidence": "EXTRACTED", "source_file": "gogcli\\internal\\cmd\\docs_comments_test.go", "source_location": "L398", "weight": 1.0}, {"source": "docs_comments_test", "target": "docs_comments_test_testdocscommentsreply_json", "relation": "contains", "confidence": "EXTRACTED", "source_file": "gogcli\\internal\\cmd\\docs_comments_test.go", "source_location": "L415", "weight": 1.0}, {"source": "docs_comments_test", "target": "docs_comments_test_testdocscommentsresolve_json", "relation": "contains", "confidence": "EXTRACTED", "source_file": "gogcli\\internal\\cmd\\docs_comments_test.go", "source_location": "L439", "weight": 1.0}, {"source": "docs_comments_test", "target": "docs_comments_test_testdocscommentsdelete_json", "relation": "contains", "confidence": "EXTRACTED", "source_file": "gogcli\\internal\\cmd\\docs_comments_test.go", "source_location": "L465", "weight": 1.0}, {"source": "docs_comments_test", "target": "docs_comments_test_testdocscomments_validationerrors", "relation": "contains", "confidence": "EXTRACTED", "source_file": "gogcli\\internal\\cmd\\docs_comments_test.go", "source_location": "L491", "weight": 1.0}, {"source": "docs_comments_test", "target": "docs_comments_test_testfilteropencomments", "relation": "contains", "confidence": "EXTRACTED", "source_file": "gogcli\\internal\\cmd\\docs_comments_test.go", "source_location": "L537", "weight": 1.0}, {"source": "docs_comments_test", "target": "docs_comments_test_testfilteropencomments_allopen", "relation": "contains", "confidence": "EXTRACTED", "source_file": "gogcli\\internal\\cmd\\docs_comments_test.go", "source_location": "L553", "weight": 1.0}, {"source": "docs_comments_test", "target": "docs_comments_test_testfilteropencomments_allresolved", "relation": "contains", "confidence": "EXTRACTED", "source_file": "gogcli\\internal\\cmd\\docs_comments_test.go", "source_location": "L563", "weight": 1.0}, {"source": "docs_comments_test", "target": "docs_comments_test_testfilteropencomments_nil", "relation": "contains", "confidence": "EXTRACTED", "source_file": "gogcli\\internal\\cmd\\docs_comments_test.go", "source_location": "L573", "weight": 1.0}, {"source": "docs_comments_test", "target": "docs_comments_test_testfilteropencomments_nilelements", "relation": "contains", "confidence": "EXTRACTED", "source_file": "gogcli\\internal\\cmd\\docs_comments_test.go", "source_location": "L580", "weight": 1.0}, {"source": "docs_comments_test_testdocscommentslist_filtersresolved", "target": "docs_comments_test_newcommentstestserver", "relation": "calls", "confidence": "EXTRACTED", "source_file": "gogcli\\internal\\cmd\\docs_comments_test.go", "source_location": "L190", "weight": 1.0}, {"source": "docs_comments_test_testdocscommentslist_filtersresolved", "target": "docs_comments_test_setupdriveservicefromserver", "relation": "calls", "confidence": "EXTRACTED", "source_file": "gogcli\\internal\\cmd\\docs_comments_test.go", "source_location": "L192", "weight": 1.0}, {"source": "docs_comments_test_testdocscommentslist_includeresolved", "target": "docs_comments_test_newcommentstestserver", "relation": "calls", "confidence": "EXTRACTED", "source_file": "gogcli\\internal\\cmd\\docs_comments_test.go", "source_location": "L223", "weight": 1.0}, {"source": "docs_comments_test_testdocscommentslist_includeresolved", "target": "docs_comments_test_setupdriveservicefromserver", "relation": "calls", "confidence": "EXTRACTED", "source_file": "gogcli\\internal\\cmd\\docs_comments_test.go", "source_location": "L225", "weight": 1.0}, {"source": "docs_comments_test_testdocscommentslist_plaintext", "target": "docs_comments_test_newcommentstestserver", "relation": "calls", "confidence": "EXTRACTED", "source_file": "gogcli\\internal\\cmd\\docs_comments_test.go", "source_location": "L247", "weight": 1.0}, {"source": "docs_comments_test_testdocscommentslist_plaintext", "target": "docs_comments_test_setupdriveservicefromserver", "relation": "calls", "confidence": "EXTRACTED", "source_file": "gogcli\\internal\\cmd\\docs_comments_test.go", "source_location": "L249", "weight": 1.0}, {"source": "docs_comments_test_testdocscommentslist_scanspagesforopencomments", "target": "docs_comments_test_newcommentstestserver", "relation": "calls", "confidence": "EXTRACTED", "source_file": "gogcli\\internal\\cmd\\docs_comments_test.go", "source_location": "L277", "weight": 1.0}, {"source": "docs_comments_test_testdocscommentslist_scanspagesforopencomments", "target": "docs_comments_test_setupdriveservicefromserver", "relation": "calls", "confidence": "EXTRACTED", "source_file": "gogcli\\internal\\cmd\\docs_comments_test.go", "source_location": "L279", "weight": 1.0}, {"source": "docs_comments_test_testdocscommentslist_empty", "target": "docs_comments_test_newcommentstestserver", "relation": "calls", "confidence": "EXTRACTED", "source_file": "gogcli\\internal\\cmd\\docs_comments_test.go", "source_location": "L301", "weight": 1.0}, {"source": "docs_comments_test_testdocscommentslist_empty", "target": "docs_comments_test_setupdriveservicefromserver", "relation": "calls", "confidence": "EXTRACTED", "source_file": "gogcli\\internal\\cmd\\docs_comments_test.go", "source_location": "L303", "weight": 1.0}, {"source": "docs_comments_test_testdocscommentsget_json", "target": "docs_comments_test_newcommentstestserver", "relation": "calls", "confidence": "EXTRACTED", "source_file": "gogcli\\internal\\cmd\\docs_comments_test.go", "source_location": "L316", "weight": 1.0}, {"source": "docs_comments_test_testdocscommentsget_json", "target": "docs_comments_test_setupdriveservicefromserver", "relation": "calls", "confidence": "EXTRACTED", "source_file": "gogcli\\internal\\cmd\\docs_comments_test.go", "source_location": "L318", "weight": 1.0}, {"source": "docs_comments_test_testdocscommentsget_plain", "target": "docs_comments_test_newcommentstestserver", "relation": "calls", "confidence": "EXTRACTED", "source_file": "gogcli\\internal\\cmd\\docs_comments_test.go", "source_location": "L343", "weight": 1.0}, {"source": "docs_comments_test_testdocscommentsget_plain", "target": "docs_comments_test_setupdriveservicefromserver", "relation": "calls", "confidence": "EXTRACTED", "source_file": "gogcli\\internal\\cmd\\docs_comments_test.go", "source_location": "L345", "weight": 1.0}, {"source": "docs_comments_test_testdocscommentsadd_json", "target": "docs_comments_test_newcommentstestserver", "relation": "calls", "confidence": "EXTRACTED", "source_file": "gogcli\\internal\\cmd\\docs_comments_test.go", "source_location": "L369", "weight": 1.0}, {"source": "docs_comments_test_testdocscommentsadd_json", "target": "docs_comments_test_setupdriveservicefromserver", "relation": "calls", "confidence": "EXTRACTED", "source_file": "gogcli\\internal\\cmd\\docs_comments_test.go", "source_location": "L371", "weight": 1.0}, {"source": "docs_comments_test_testdocscommentsadd_plain", "target": "docs_comments_test_newcommentstestserver", "relation": "calls", "confidence": "EXTRACTED", "source_file": "gogcli\\internal\\cmd\\docs_comments_test.go", "source_location": "L399", "weight": 1.0}, {"source": "docs_comments_test_testdocscommentsadd_plain", "target": "docs_comments_test_setupdriveservicefromserver", "relation": "calls", "confidence": "EXTRACTED", "source_file": "gogcli\\internal\\cmd\\docs_comments_test.go", "source_location": "L401", "weight": 1.0}, {"source": "docs_comments_test_testdocscommentsreply_json", "target": "docs_comments_test_newcommentstestserver", "relation": "calls", "confidence": "EXTRACTED", "source_file": "gogcli\\internal\\cmd\\docs_comments_test.go", "source_location": "L416", "weight": 1.0}, {"source": "docs_comments_test_testdocscommentsreply_json", "target": "docs_comments_test_setupdriveservicefromserver", "relation": "calls", "confidence": "EXTRACTED", "source_file": "gogcli\\internal\\cmd\\docs_comments_test.go", "source_location": "L418", "weight": 1.0}, {"source": "docs_comments_test_testdocscommentsresolve_json", "target": "docs_comments_test_newcommentstestserver", "relation": "calls", "confidence": "EXTRACTED", "source_file": "gogcli\\internal\\cmd\\docs_comments_test.go", "source_location": "L440", "weight": 1.0}, {"source": "docs_comments_test_testdocscommentsresolve_json", "target": "docs_comments_test_setupdriveservicefromserver", "relation": "calls", "confidence": "EXTRACTED", "source_file": "gogcli\\internal\\cmd\\docs_comments_test.go", "source_location": "L442", "weight": 1.0}, {"source": "docs_comments_test_testdocscommentsdelete_json", "target": "docs_comments_test_newcommentstestserver", "relation": "calls", "confidence": "EXTRACTED", "source_file": "gogcli\\internal\\cmd\\docs_comments_test.go", "source_location": "L466", "weight": 1.0}, {"source": "docs_comments_test_testdocscommentsdelete_json", "target": "docs_comments_test_setupdriveservicefromserver", "relation": "calls", "confidence": "EXTRACTED", "source_file": "gogcli\\internal\\cmd\\docs_comments_test.go", "source_location": "L468", "weight": 1.0}]}