{"nodes": [{"id": "gmail_date", "label": "gmail_date.go", "file_type": "code", "source_file": "gogcli\\internal\\cmd\\gmail_date.go", "source_location": "L1"}, {"id": "gmail_date_formatgmaildateinlocation", "label": "formatGmailDateInLocation()", "file_type": "code", "source_file": "gogcli\\internal\\cmd\\gmail_date.go", "source_location": "L9"}, {"id": "gmail_date_mailparsedate", "label": "mailParseDate()", "file_type": "code", "source_file": "gogcli\\internal\\cmd\\gmail_date.go", "source_location": "L23"}], "edges": [{"source": "gmail_date", "target": "mail", "relation": "imports_from", "confidence": "EXTRACTED", "source_file": "gogcli\\internal\\cmd\\gmail_date.go", "source_location": "L4", "weight": 1.0}, {"source": "gmail_date", "target": "strings", "relation": "imports_from", "confidence": "EXTRACTED", "source_file": "gogcli\\internal\\cmd\\gmail_date.go", "source_location": "L5", "weight": 1.0}, {"source": "gmail_date", "target": "time", "relation": "imports_from", "confidence": "EXTRACTED", "source_file": "gogcli\\internal\\cmd\\gmail_date.go", "source_location": "L6", "weight": 1.0}, {"source": "gmail_date", "target": "gmail_date_formatgmaildateinlocation", "relation": "contains", "confidence": "EXTRACTED", "source_file": "gogcli\\internal\\cmd\\gmail_date.go", "source_location": "L9", "weight": 1.0}, {"source": "gmail_date", "target": "gmail_date_mailparsedate", "relation": "contains", "confidence": "EXTRACTED", "source_file": "gogcli\\internal\\cmd\\gmail_date.go", "source_location": "L23", "weight": 1.0}, {"source": "gmail_date_formatgmaildateinlocation", "target": "gmail_date_mailparsedate", "relation": "calls", "confidence": "EXTRACTED", "source_file": "gogcli\\internal\\cmd\\gmail_date.go", "source_location": "L17", "weight": 1.0}]}