{"nodes": [{"id": "execute_drive_flags_test", "label": "execute_drive_flags_test.go", "file_type": "code", "source_file": "gogcli\\internal\\cmd\\execute_drive_flags_test.go", "source_location": "L1"}, {"id": "execute_drive_flags_test_testexecute_drivels_positionalfolderrejected", "label": "TestExecute_DriveLs_PositionalFolderRejected()", "file_type": "code", "source_file": "gogcli\\internal\\cmd\\execute_drive_flags_test.go", "source_location": "L5"}, {"id": "execute_drive_flags_test_testexecute_drivemove_missingparentflag", "label": "TestExecute_DriveMove_MissingParentFlag()", "file_type": "code", "source_file": "gogcli\\internal\\cmd\\execute_drive_flags_test.go", "source_location": "L17"}, {"id": "execute_drive_flags_test_testexecute_drivemove_positionalparentrejected", "label": "TestExecute_DriveMove_PositionalParentRejected()", "file_type": "code", "source_file": "gogcli\\internal\\cmd\\execute_drive_flags_test.go", "source_location": "L29"}], "edges": [{"source": "execute_drive_flags_test", "target": "testing", "relation": "imports_from", "confidence": "EXTRACTED", "source_file": "gogcli\\internal\\cmd\\execute_drive_flags_test.go", "source_location": "L3", "weight": 1.0}, {"source": "execute_drive_flags_test", "target": "execute_drive_flags_test_testexecute_drivels_positionalfolderrejected", "relation": "contains", "confidence": "EXTRACTED", "source_file": "gogcli\\internal\\cmd\\execute_drive_flags_test.go", "source_location": "L5", "weight": 1.0}, {"source": "execute_drive_flags_test", "target": "execute_drive_flags_test_testexecute_drivemove_missingparentflag", "relation": "contains", "confidence": "EXTRACTED", "source_file": "gogcli\\internal\\cmd\\execute_drive_flags_test.go", "source_location": "L17", "weight": 1.0}, {"source": "execute_drive_flags_test", "target": "execute_drive_flags_test_testexecute_drivemove_positionalparentrejected", "relation": "contains", "confidence": "EXTRACTED", "source_file": "gogcli\\internal\\cmd\\execute_drive_flags_test.go", "source_location": "L29", "weight": 1.0}]}